{
  "nodes": [
    {
      "id": 0,
      "name": "1031",
      "x": 838,
      "y": 239
    },
    {
      "id": 1,
      "name": "1030",
      "x": 338,
      "y": 303
    },
    {
      "id": 2,
      "name": "hallway",
      "x": 871,
      "y": 630
    },
    {
      "id": 3,
      "name": "1029",
      "x": 446,
      "y": 932
    },
    {
      "id": 4,
      "name": "hall",
      "x": 900,
      "y": 950
    },
    {
      "id": 5,
      "name": "Door",
      "x": 569,
      "y": 592
    },
    {
      "id": 6,
      "name": "Door",
      "x": 458,
      "y": 787
    },
    {
      "id": 7,
      "name": "Door",
      "x": 577,
      "y": 792
    },
    {
      "id": 10,
      "name": "1032",
      "x": 1337,
      "y": 303
    },
    {
      "id": 12,
      "name": "hallway",
      "x": 1449,
      "y": 795
    },
    {
      "id": 13,
      "name": "1036",
      "x": 1137,
      "y": 900
    },
    {
      "id": 14,
      "name": "stairs",
      "x": 1440,
      "y": 918
    },
    {
      "id": 17,
      "name": "Door",
      "x": 1026,
      "y": 862
    },
    {
      "id": 18,
      "name": "Door",
      "x": 1122,
      "y": 605
    },
    {
      "id": 19,
      "name": "Door",
      "x": 672,
      "y": 523
    },
    {
      "id": 20,
      "name": "Door",
      "x": 1105,
      "y": 779
    },
    {
      "id": 30,
      "name": "Door",
      "x": 1055,
      "y": 445
    },
    {
      "id": 31,
      "name": "Door",
      "x": 1207,
      "y": 807
    },
    {
      "id": 33,
      "name": "Door",
      "x": 1615,
      "y": 789
    }
  ],
  "edges": [
    {
      "id_1": 0,
      "id_2": 30
    },
    {
      "id_1": 1,
      "id_2": 5
    },
    {
      "id_1": 2,
      "id_2": 5
    },
    {
      "id_1": 2,
      "id_2": 6
    },
    {
      "id_1": 2,
      "id_2": 7
    },
    {
      "id_1": 2,
      "id_2": 18
    },
    {
      "id_1": 2,
      "id_2": 19
    },
    {
      "id_1": 2,
      "id_2": 30
    },
    {
      "id_1": 2,
      "id_2": 4
    },
    {
      "id_1": 2,
      "id_2": 12
    },
    {
      "id_1": 3,
      "id_2": 6
    },
    {
      "id_1": 4,
      "id_2": 17
    },
    {
      "id_1": 4,
      "id_2": 20
    },
    {
      "id_1": 4,
      "id_2": 14
    },
    {
      "id_1": 4,
      "id_2": 12
    },
    {
      "id_1": 10,
      "id_2": 30
    },
    {
      "id_1": 12,
      "id_2": 31
    },
    {
      "id_1": 12,
      "id_2": 33
    },
    {
      "id_1": 12,
      "id_2": 14
    },
    {
      "id_1": 13,
      "id_2": 31
    }
  ]
}